hcp/__init__.py
hcp/client.py
hcp_vault_secrets_wrapper-0.7.5.dist-info/METADATA
hcp_vault_secrets_wrapper-0.7.5.dist-info/WHEEL
hcp_vault_secrets_wrapper-0.7.5.dist-info/licenses/LICENSE
hcp_vault_secrets_wrapper-0.7.5.dist-info/RECORD
